there/__main__.py
there/fuse_drive.py
there/jupyter-setup.py
there/kernel.py
there/miniterm_mpy.py
there/os_error_list.py
there/repl_connection.py
there/speaking.py
there/string_escape.py
there/sync.py
there/walk.py
mpy_repl_tool-0.14.dist-info/LICENSE.txt
mpy_repl_tool-0.14.dist-info/METADATA
mpy_repl_tool-0.14.dist-info/WHEEL
mpy_repl_tool-0.14.dist-info/entry_points.txt
mpy_repl_tool-0.14.dist-info/top_level.txt
mpy_repl_tool-0.14.dist-info/RECORD
