Metadata-Version: 2.1
Name: mpy-repl-tool
Version: 0.14
Summary: Communicate and transfer files from and to MicroPython boards via REPL
Home-page: https://github.com/zsquareplusc/mpy-repl-tool
Author: Chris Liechti
Author-email: cliechti@gmx.net
License: BSD
Platform: any
Classifier: Development Status :: 5 - Production/Stable
Classifier: Environment :: Console
Classifier: Intended Audience :: Developers
Classifier: License :: OSI Approved :: BSD License
Classifier: Operating System :: MacOS
Classifier: Operating System :: POSIX
Classifier: Operating System :: Microsoft :: Windows
Classifier: Programming Language :: Python :: 3 :: Only
Classifier: Topic :: Software Development :: Embedded Systems
License-File: LICENSE.txt
Requires-Dist: pyserial >=3
Requires-Dist: colorama
Provides-Extra: mount
Requires-Dist: fusepy ; extra == 'mount'
